dotjson/__init__.py
dotjson/main.py
dotjson-0.1.2.dist-info/WHEEL
dotjson-0.1.2.dist-info/METADATA
dotjson-0.1.2.dist-info/RECORD
