Metadata-Version: 2.1
Name: dotjson
Version: 0.1.2
Summary: Read key-value pairs from a settings.json file and set them as environment variables, dictionary or Pydantic models
Home-page: https://github.com/aakashkhanna/python-dotjson
Author: Aakash Khanna
Author-email: aakashkh13@gmail.com
Requires-Python: >=3.8,<4.0
Classifier: Development Status :: 5 - Production/Stable
Classifier: Environment :: Web Environment
Classifier: Intended Audience :: Developers
Classifier: Intended Audience :: System Administrators
Classifier: Operating System :: OS Independent
Classifier: Programming Language :: Python
Classifier: Programming Language :: Python :: 3
Classifier: Programming Language :: Python :: 3.10
Classifier: Programming Language :: Python :: 3.11
Classifier: Programming Language :: Python :: 3.8
Classifier: Programming Language :: Python :: 3.9
Classifier: Programming Language :: Python :: Implementation :: PyPy
Classifier: Topic :: System :: Systems Administration
Classifier: Topic :: Utilities
Requires-Dist: flatten-json (>=0.1.13,<0.2.0)
Requires-Dist: pydantic (>=1.9.1,<2.0.0)
Requires-Dist: pytest (>=7.1.2,<8.0.0)
Requires-Dist: pytest-cov (>=3.0.0,<4.0.0)
Requires-Dist: pytest-md-report (>=0.2.0,<0.3.0)
Project-URL: Documentation, https://github.com/aakashkhanna/python-dotjson#readme
Project-URL: Repository, https://github.com/aakashkhanna/python-dotjson
